certcloner/__about__.py
certcloner/__init__.py
certcloner/main.py
certcloner-2024.3.11.dist-info/METADATA
certcloner-2024.3.11.dist-info/WHEEL
certcloner-2024.3.11.dist-info/entry_points.txt
certcloner-2024.3.11.dist-info/licenses/LICENSE.txt
certcloner-2024.3.11.dist-info/RECORD
