Metadata-Version: 2.1
Name: certcloner
Version: 2024.3.11
Summary: Clones certificates with keys you control
Project-URL: Documentation, https://github.com/magnuswatn/certcloner#readme
Project-URL: Issues, https://github.com/magnuswatn/certcloner/issues
Project-URL: Source, https://github.com/magnuswatn/certcloner
Author-email: Magnus Watn <magnus@watn.no>
License-Expression: MIT
License-File: LICENSE.txt
Classifier: Development Status :: 4 - Beta
Classifier: Programming Language :: Python
Classifier: Programming Language :: Python :: 3.10
Classifier: Programming Language :: Python :: 3.11
Classifier: Programming Language :: Python :: 3.12
Classifier: Programming Language :: Python :: Implementation :: CPython
Classifier: Programming Language :: Python :: Implementation :: PyPy
Requires-Python: >=3.10
Requires-Dist: click
Requires-Dist: cryptography>=42.0.0
